commoncode/__init__.py
commoncode/archive.py
commoncode/cliutils.py
commoncode/codec.py
commoncode/command.py
commoncode/compat.py
commoncode/datautils.py
commoncode/date.py
commoncode/dict_utils.ABOUT
commoncode/dict_utils.py
commoncode/distro.py
commoncode/fetch.py
commoncode/fileset.py
commoncode/filetype.py
commoncode/fileutils.py
commoncode/fileutils.py.ABOUT
commoncode/functional.py
commoncode/hash.py
commoncode/ignore.py
commoncode/paths.py
commoncode/python.LICENSE
commoncode/resource.py
commoncode/system.py
commoncode/testcase.py
commoncode/text.py
commoncode/timeutils.py
commoncode/urn.py
commoncode/version.py
commoncode-32.4.2.dist-info/licenses/AUTHORS.rst
commoncode-32.4.2.dist-info/licenses/CHANGELOG.rst
commoncode-32.4.2.dist-info/licenses/CODE_OF_CONDUCT.rst
commoncode-32.4.2.dist-info/licenses/NOTICE
commoncode-32.4.2.dist-info/licenses/README.rst
commoncode-32.4.2.dist-info/licenses/apache-2.0.LICENSE
commoncode-32.4.2.dist-info/licenses/commoncode.ABOUT
commoncode-32.4.2.dist-info/METADATA
commoncode-32.4.2.dist-info/WHEEL
commoncode-32.4.2.dist-info/top_level.txt
commoncode-32.4.2.dist-info/RECORD
